map_my_locations/__init__.py
map_my_locations/cli.py
map_my_locations/mapper.py
map_my_locations-0.1.0.dist-info/licenses/LICENSE
map_my_locations-0.1.0.dist-info/METADATA
map_my_locations-0.1.0.dist-info/WHEEL
map_my_locations-0.1.0.dist-info/entry_points.txt
map_my_locations-0.1.0.dist-info/top_level.txt
map_my_locations-0.1.0.dist-info/RECORD
