Metadata-Version: 2.4
Name: map-my-locations
Version: 0.1.0
Summary: CLI tool to plot location routes on a map
Author-email: Rishab Sharma <rishab.sharma97501@gmail.com>
Requires-Python: >=3.7
License-File: LICENSE
Requires-Dist: folium>=0.12.0
Dynamic: license-file
